LICENSE
benchling_sdk/__init__.py
benchling_sdk/apps/__init__.py
benchling_sdk/apps/canvas/__init__.py
benchling_sdk/apps/canvas/errors.py
benchling_sdk/apps/canvas/framework.py
benchling_sdk/apps/canvas/types.py
benchling_sdk/apps/config/__init__.py
benchling_sdk/apps/config/cryptography_helpers.py
benchling_sdk/apps/config/decryption_provider.py
benchling_sdk/apps/config/errors.py
benchling_sdk/apps/config/framework.py
benchling_sdk/apps/config/helpers.py
benchling_sdk/apps/config/mock_config.py
benchling_sdk/apps/config/types.py
benchling_sdk/apps/framework.py
benchling_sdk/apps/helpers/__init__.py
benchling_sdk/apps/helpers/manifest_helpers.py
benchling_sdk/apps/helpers/webhook_helpers.py
benchling_sdk/apps/status/__init__.py
benchling_sdk/apps/status/errors.py
benchling_sdk/apps/status/framework.py
benchling_sdk/apps/status/helpers.py
benchling_sdk/apps/status/types.py
benchling_sdk/apps/types.py
benchling_sdk/auth/__init__.py
benchling_sdk/auth/api_key_auth.py
benchling_sdk/auth/bearer_token_auth.py
benchling_sdk/auth/client_credentials_oauth2.py
benchling_sdk/benchling.py
benchling_sdk/docs/__init__.py
benchling_sdk/docs/__main__.py
benchling_sdk/errors.py
benchling_sdk/helpers/__init__.py
benchling_sdk/helpers/client_helpers.py
benchling_sdk/helpers/constants.py
benchling_sdk/helpers/decorators.py
benchling_sdk/helpers/file_helpers.py
benchling_sdk/helpers/logging_helpers.py
benchling_sdk/helpers/package_helpers.py
benchling_sdk/helpers/pagination_helpers.py
benchling_sdk/helpers/response_helpers.py
benchling_sdk/helpers/retry_helpers.py
benchling_sdk/helpers/serialization_helpers.py
benchling_sdk/helpers/task_helpers.py
benchling_sdk/helpers/transaction_manager.py
benchling_sdk/models/__init__.py
benchling_sdk/models/webhooks/__init__.py
benchling_sdk/models/webhooks/v0/__init__.py
benchling_sdk/py.typed
benchling_sdk/services/__init__.py
benchling_sdk/services/v2/__init__.py
benchling_sdk/services/v2/alpha/__init__.py
benchling_sdk-1.23.1.dist-info/LICENSE
benchling_sdk-1.23.1.dist-info/METADATA
benchling_sdk-1.23.1.dist-info/WHEEL
benchling_sdk-1.23.1.dist-info/RECORD
